<?xml version="1.0" encoding="utf-8"?>
<database name="default" defaultIdMethod="native" namespace="\models" defaultPhpNamingMethod="underscore">
  <table name="users" idMethod="native" phpName="Users" namespace="\models">
    <column name="id" phpName="Id" type="INTEGER" primaryKey="true" autoIncrement="true" required="true"/>
    <column name="email" phpName="Email" type="VARCHAR" size="50" required="true"/>
    <column name="vorname" phpName="Vorname" type="VARCHAR" size="30" required="true"/>
    <column name="nachname" phpName="Nachname" type="VARCHAR" size="50" required="true"/>
    <column name="anzahl_logins" phpName="AnzahlLogins" type="INTEGER" required="true"/>
    <vendor type="mysql">
      <parameter name="Engine" value="InnoDB"/>
    </vendor>
  </table>
</database>